v2/spi_recieve.v
`timescale 1ns / 1ps
//////////////////////////////////////////////////////////////////////////////////
// Company: 
// Engineer: 
// 
// Create Date:    13:36:55 05/09/2011 
// Design Name: spi_revieve
// Module Name:    spi_recieve 
// Project Name: 
// Target Devices: 
// Tool versions: 
// Description: to recieve data from SDCS7476 (Pmod AD1)
//
// Dependencies: 
//
// Revision: 1.1
// Revision 0.01 - File Created
// Additional Comments: 
//
//////////////////////////////////////////////////////////////////////////////////
/*
-------------------------------------------------------------------------
--Title         : AD1 Reference Component
--
--   Inputs         : 5
--   Outputs        : 5
--
--   Description: This is the AD1 Reference Component entity. The input
--                ports are a 50 MHz clock and an asynchronous reset 
--                button along with the data from the ADC7476 that 
--                is serially shifted in on each clock cycle(SDATA1 and
--                SDATA2). The outputs are the SCLK signal which clocks
--                the PMOD-AD1 board at 12.5 MHz and a chip select 
--                signal (nCS) that enables the ADC7476 chips on the
--                PMOD-AD1 board as well as two 12-bit output 
--                vectors labeled DATA1 and DATA2 which can be used by 
--                any external components. The START is used to tell
--                the component when to start a conversion. After a
--                conversion is done the component activates the DONE
--                signal.
--
--------------------------------------------------------------------------
*/

module spi_recieve(
//general usage
clk,
rst,
//Pmod interface signals
sdata1,
sdata2,
sclk,
ncs,
//user interface signals
data1,
data2,
start,
done
    );

/*
--------------------------------------------------------------------------------
-- Title            : Local signal assignments
--
-- Description      : The following signals will be used to drive the  
--                    processes of this VHDL file.
--
--   current_state : This signal will be the pointer that will point at the
--                   current state of the Finite State Machine of the 
--                   controller.
--   next_state    : This signal will be the pointer that will point at the
--                   current state of the Finite State Machine of the 
--                   controller.
--   temp1         : This is a 16-bit vector that will store the 16-bits of data 
--                   that are serially shifted-in form the  first ADC7476 chip
--                   inside the PMOD-AD1 board.
--   temp2         : This is a 16-bit vector that will store the 16-bits of data 
--                   that are serially shifted-in form the second ADC7476 chip 
--                   inside the PMOD-AD1 board.
--   clk_div       : This will be the divided 12.5 MHz clock signal that will
--                   clock the PMOD-AD1 board
--   clk_counter   : This counter will be used to create a divided clock signal.
--
--   shiftCounter  : This counter will be used to count the shifted data from  
--                   the ADC7476 chip inside the PMOD-AD1 board.
--   enShiftCounter: This signal will be used to enable the counter for the  
--                   shifted data from the ADC7476 chip inside the PMOD-AD1.
--   enParalelLoad : This signal will be used to enable the load the shifted  
--                   data in a register.
--------------------------------------------------------------------------------
*/
parameter Idle=2'b00;
parameter ShiftIn=2'b01;
parameter SyncData=2'b11;

input         clk,rst,sdata1,sdata2,start;
output [11:0] data1;
output [11:0] data2;
output        sclk,ncs,done;

reg [11:0] data1;
reg [11:0] data2;
reg        sclk,sclk_tmp,ncs,done;

reg [1:0]  current_state,next_state;
reg [15:0] temp1,temp2;
reg        clk_div,clk_div_tmp;
reg [2:0]  clk_counter,clk_counter_tmp;
reg [3:0]  shiftCounter;
reg        enShiftCounter;
reg        enParalelLoad;

/*
--------------------------------------------------------------------------------
-- Title          :     clock divider process
--
-- Description    : This is the process that will divide the 50 MHz clock 
--                  down to a clock speed of 12.5 MHz to drive the ADC7476 chip. 
-------------------------------------------------------------------------------- 
*/
always @ (posedge clk or posedge rst)
begin
if (rst==1)
	clk_counter<=3'b000;
else
	clk_counter<=clk_counter_tmp;
end

always @ (clk_counter or clk_div or sclk)
begin
if (clk_counter==3'b001)
	begin
	clk_counter_tmp=3'b000;
	clk_div_tmp=~clk_div;
	sclk_tmp=~sclk;
	end
else
	begin
	clk_counter_tmp=clk_counter+1;
	clk_div_tmp=clk_div;
	sclk_tmp=sclk;
	end
end

always @ (posedge clk or posedge rst)
begin
if (rst)
	begin
	clk_div=0;
	sclk   =0;
	end
else
	begin
	clk_div=clk_div_tmp;
	sclk   =sclk_tmp;
	end
end

/*
-----------------------------------------------------------------------------------
--
-- Title      : counter
--
-- Description: This is the process were the converted data will be colected and
--              output.When the enShiftCounter is activated, the 16-bits of data  
--              from the ADC7476 chips will be shifted inside the temporary 
--              registers. A 4-bit counter is used to keep shifting the data 
--              inside temp1 and temp2 for 16 clock cycles. When the enParalelLoad
--              signal is generated inside the SyncData state, the converted data 
--              in the temporary shift registers will be placed on the outputs 
--              DATA1 and DATA2. 
--    
-----------------------------------------------------------------------------------    
*/

always @ (posedge clk_div)
begin
if(enShiftCounter==1)
	begin
	temp1<={temp1[14:0],sdata1};
	temp2<={temp2[14:0],sdata2};
	shiftCounter<=shiftCounter+1;
	data1<=data1;
   data2<=data2;

	end
else if (enParalelLoad==1)
	begin
	temp1<=temp1;
	temp2<=temp2;
	shiftCounter<=4'b0000;
	data1<=temp1[12:1];
	data2<=temp2[12:1];
	end
else
	begin
	temp1<=temp1;
	temp2<=temp2;
	shiftCounter<=4'b0000;
	data1<=data1;
   data2<=data2;
	end
end

/*
---------------------------------------------------------------------------------
--
-- Title      : Finite State Machine
--
-- Description: This 3 processes represent the FSM that contains three states.
--              The first state is the Idle state in which a temporary registers
--              are assigned the updated value of the input "DATA1" and "DATA2".
--              The next state is the ShiftIn state where the 16-bits of data
--              from each of the ADCS7476 chips are left shifted in the temp1
--              and temp2 shift registers. The third state, SyncData drives the
--              output signal nCS high for 1 clock period maintainig nCS high  
--              also in the Idle state telling the ADCS7476 to mark the end of
--              the conversion.
-- Notes:         The data will change on the lower edge of the clock signal. There 
--                     is also an asynchronous reset that will reset all signals to  
--                     their original state.
--
-----------------------------------------------------------------------------------        
        
-----------------------------------------------------------------------------------
--
-- Title      : SYNC_PROC
--
-- Description: This is the process were the states are changed synchronously. At 
--              reset the current state becomes Idle state.
--    
-----------------------------------------------------------------------------------   
*/

always @(posedge clk_div)
begin
if(rst)
	current_state<=Idle;
else
	current_state<=next_state;
end

/*
-----------------------------------------------------------------------------------
--
-- Title      : OUTPUT_DECODE
--
-- Description: This is the process were the output signals are generated
--              unsynchronously based on the state only (Moore State Machine).
--    
-----------------------------------------------------------------------------------      
*/

always @ (current_state)
begin
if(current_state==Idle)
	begin
	enShiftCounter=0;
	done=1;
	ncs=1;
	enParalelLoad=0;
	end
else if (current_state==ShiftIn)
	begin
	enShiftCounter=1;
	done=0;
	ncs=0;
	enParalelLoad=0;
	end
else
	begin
	enShiftCounter=0;
	done=0;
	ncs=1;
	enParalelLoad=1;
	end
end

/*
----------------------------------------------------------------------------------
--
-- Title      : NEXT_STATE_DECODE
--
-- Description: This is the process were the next state logic is generated 
--              depending on the current state and the input signals.
--    
-----------------------------------------------------------------------------------    
*/

always @ (current_state or start or shiftCounter)
begin
case (current_state)
	Idle:    begin if (start==1)              next_state=ShiftIn;  else next_state=current_state; end
	ShiftIn: begin if (shiftCounter==4'b1111) next_state=SyncData; else next_state=current_state; end
	SyncData:begin if (start==0)              next_state=Idle;     else next_state=current_state; end
	default: begin                                                       next_state=Idle; end
endcase
end


endmodule

v2/t_spi_receive.v
`timescale 1ns / 1ps
module t_spi_receive;
    
    parameter CLK_CYCLE=10;

	// Inputs
        reg         clk,rst,sdata1,sdata2,start;

	// Outputs
        wire [11:0] data1;
        wire [11:0] data2;
        wire        sclk,ncs,done;

	// Instantiate the Unit Under Test (UUT)
        spi_recieve dut(
        //general usage
        clk,
        rst,
        //Pmod interface signals
        sdata1,
        sdata2,
        sclk,
        ncs,
        //user interface signals
        data1,
        data2,
        start,
        done
        );
	
    task reset; begin
    #10; rst=1;
    #10; rst=0;
    end
    endtask


    task randin; begin
        @ (posedge clk); #1;
        sdata1 = $random%100;
        sdata2 = $random%100;
        start = $random%2;
    end
    endtask

    initial
     begin
     $dumpfile("test.vcd");
     $dumpvars(0,dut);
     end


	initial begin
		// Initialize Inputs
		clk=0;
        
		// Add stimulus here
        reset;
        randin;
        randin;
        randin;
        randin;
        randin;
        randin;
        randin;
        randin;
        randin;
        randin;
        randin;
        randin;
        randin;
        randin;
        randin;
        randin;
        randin;
        randin;
        randin;
        randin;
        randin;
        randin;
        randin;
        randin;
        randin;
        randin;
        randin;
        randin;
        randin;
        randin;
        randin;
        randin;
        randin;
        randin;
        randin;
        randin;
        randin;
        randin;
        randin;
        randin;
        randin;
        randin;
        randin;
        randin;
        randin;
        randin;
        randin;
        randin;
        randin;
        randin;
        randin;
        randin;
        randin;
        randin;
        randin;
        randin;
        randin;
        randin;
        randin;
        randin;
        randin;
        randin;
        randin;
        randin;
        randin;
        randin;
        randin;
        randin;
        randin;
        randin;
        randin;
        randin;
        randin;
        randin;
        randin;
        randin;
        randin;
        randin;
        randin;
        randin;
        randin;
        randin;
        randin;
        randin;
        randin;
        randin;
        randin;
        randin;
        randin;
        randin;
        randin;
        randin;
        randin;
        randin;
        randin;
        randin;
        randin;
        randin;
        randin;
        randin;
        randin;
        randin;
        randin;
        randin;
        randin;
        randin;
        randin;
        randin;
        randin;
        randin;
        randin;
        randin;
        randin;
        randin;
        randin;
        randin;
        randin;
        randin;
        randin;
        randin;
        randin;
        randin;
        randin;
        randin;
        randin;
        randin;
        randin;
        randin;
        randin;
        randin;
        randin;
        randin;
        randin;
        randin;
        randin;
        randin;
        randin;
        randin;
        randin;
        randin;
        randin;
        randin;
        #10; $finish;


	end


    always #(CLK_CYCLE/2) clk=~clk;
    

      
endmodule

v2/test.vcd
$date
	Tue Oct  9 21:41:05 2012
$end
$version
	Icarus Verilog
$end
$timescale
	1ps
$end
$scope module t_spi_receive $end
$scope module dut $end
$var wire 1 ! clk $end
$var wire 1 " rst $end
$var wire 1 # sdata1 $end
$var wire 1 $ sdata2 $end
$var wire 1 % start $end
$var reg 3 & clk_counter [2:0] $end
$var reg 3 ' clk_counter_tmp [2:0] $end
$var reg 1 ( clk_div $end
$var reg 1 ) clk_div_tmp $end
$var reg 2 * current_state [1:0] $end
$var reg 12 + data1 [11:0] $end
$var reg 12 , data2 [11:0] $end
$var reg 1 - done $end
$var reg 1 . enParalelLoad $end
$var reg 1 / enShiftCounter $end
$var reg 1 0 ncs $end
$var reg 2 1 next_state [1:0] $end
$var reg 1 2 sclk $end
$var reg 1 3 sclk_tmp $end
$var reg 4 4 shiftCounter [3:0] $end
$var reg 16 5 temp1 [15:0] $end
$var reg 16 6 temp2 [15:0] $end
$upscope $end
$upscope $end
$enddefinitions $end
#0
$dumpvars
bx 6
bx 5
bx 4
x3
x2
bx 1
x0
x/
x.
x-
bx ,
bx +
bx *
x)
x(
bx '
bx &
x%
x$
x#
x"
0!
$end
#5000
1!
#10000
b1 '
b0 &
03
0)
02
0(
0!
1"
#15000
1!
#20000
0!
0"
#25000
13
1)
b0 '
b1 &
1!
#26000
b0 1
1%
1$
0#
#30000
0!
#35000
b1 1
0.
10
1-
0/
b1 '
b0 4
b0 *
b0 &
13
1)
12
1(
1!
#36000
1#
#40000
0!
#45000
03
0)
b0 '
b1 &
1!
#46000
0$
#50000
0!
#55000
b1 '
b0 &
03
0)
02
0(
1!
#60000
0!
#65000
13
1)
b0 '
b1 &
1!
#70000
0!
#75000
00
0-
1/
b1 '
b1 *
b0 &
13
1)
12
1(
1!
#76000
0%
1$
0#
#80000
0!
#85000
03
0)
b0 '
b1 &
1!
#86000
1#
#90000
0!
#95000
b1 '
b0 &
03
0)
02
0(
1!
#96000
0$
#100000
0!
#105000
13
1)
b0 '
b1 &
1!
#106000
1$
0#
#110000
0!
#115000
b1 '
b1 4
bx1 6
bx0 5
b0 &
13
1)
12
1(
1!
#116000
1%
1#
#120000
0!
#125000
03
0)
b0 '
b1 &
1!
#126000
0%
0$
#130000
0!
#135000
b1 '
b0 &
03
0)
02
0(
1!
#136000
1%
0#
#140000
0!
#145000
13
1)
b0 '
b1 &
1!
#146000
1$
#150000
0!
#155000
b1 '
b10 4
bx11 6
bx00 5
b0 &
13
1)
12
1(
1!
#156000
1#
#160000
0!
#165000
03
0)
b0 '
b1 &
1!
#166000
0$
0#
#170000
0!
#175000
b1 '
b0 &
03
0)
02
0(
1!
#176000
0%
1$
1#
#180000
0!
#185000
13
1)
b0 '
b1 &
1!
#186000
0$
0#
#190000
0!
#195000
b1 '
b11 4
bx110 6
bx000 5
b0 &
13
1)
12
1(
1!
#196000
1$
#200000
0!
#205000
03
0)
b0 '
b1 &
1!
#206000
1%
#210000
0!
#215000
b1 '
b0 &
03
0)
02
0(
1!
#216000
0%
0$
#220000
0!
#225000
13
1)
b0 '
b1 &
1!
#226000
1%
#230000
0!
#235000
b1 '
b100 4
bx1100 6
bx0000 5
b0 &
13
1)
12
1(
1!
#236000
1$
1#
#240000
0!
#245000
03
0)
b0 '
b1 &
1!
#246000
0%
0$
#250000
0!
#255000
b1 '
b0 &
03
0)
02
0(
1!
#256000
1%
1$
#260000
0!
#265000
13
1)
b0 '
b1 &
1!
#266000
0$
0#
#270000
0!
#275000
b1 '
b101 4
bx11000 6
bx00000 5
b0 &
13
1)
12
1(
1!
#276000
1#
#280000
0!
#285000
03
0)
b0 '
b1 &
1!
#290000
0!
#295000
b1 '
b0 &
03
0)
02
0(
1!
#296000
0%
1$
#300000
0!
#305000
13
1)
b0 '
b1 &
1!
#310000
0!
#315000
b1 '
b110 4
bx110001 6
bx000001 5
b0 &
13
1)
12
1(
1!
#316000
0$
0#
#320000
0!
#325000
03
0)
b0 '
b1 &
1!
#326000
1$
1#
#330000
0!
#335000
b1 '
b0 &
03
0)
02
0(
1!
#336000
1%
0#
#340000
0!
#345000
13
1)
b0 '
b1 &
1!
#346000
1#
#350000
0!
#355000
b1 '
b111 4
bx1100011 6
bx0000011 5
b0 &
13
1)
12
1(
1!
#356000
0#
#360000
0!
#365000
03
0)
b0 '
b1 &
1!
#366000
0%
0$
1#
#370000
0!
#375000
b1 '
b0 &
03
0)
02
0(
1!
#376000
0#
#380000
0!
#385000
13
1)
b0 '
b1 &
1!
#386000
1%
#390000
0!
#395000
b1 '
b1000 4
bx11000110 6
bx00000110 5
b0 &
13
1)
12
1(
1!
#396000
1$
1#
#400000
0!
#405000
03
0)
b0 '
b1 &
1!
#406000
0$
#410000
0!
#415000
b1 '
b0 &
03
0)
02
0(
1!
#416000
0%
#420000
0!
#425000
13
1)
b0 '
b1 &
1!
#426000
1$
#430000
0!
#435000
b1 '
b1001 4
bx110001101 6
bx000001101 5
b0 &
13
1)
12
1(
1!
#436000
1%
#440000
0!
#445000
03
0)
b0 '
b1 &
1!
#446000
0%
0$
#450000
0!
#455000
b1 '
b0 &
03
0)
02
0(
1!
#456000
1$
0#
#460000
0!
#465000
13
1)
b0 '
b1 &
1!
#466000
1%
0$
#470000
0!
#475000
b1 '
b1010 4
bx1100011010 6
bx0000011010 5
b0 &
13
1)
12
1(
1!
#476000
0%
1#
#480000
0!
#485000
03
0)
b0 '
b1 &
1!
#490000
0!
#495000
b1 '
b0 &
03
0)
02
0(
1!
#496000
1$
0#
#500000
0!
#505000
13
1)
b0 '
b1 &
1!
#510000
0!
#515000
b1 '
b1011 4
bx11000110101 6
bx00000110100 5
b0 &
13
1)
12
1(
1!
#516000
1%
1#
#520000
0!
#525000
03
0)
b0 '
b1 &
1!
#526000
0%
#530000
0!
#535000
b1 '
b0 &
03
0)
02
0(
1!
#536000
1%
0$
0#
#540000
0!
#545000
13
1)
b0 '
b1 &
1!
#550000
0!
#555000
b1 '
b1100 4
bx110001101010 6
bx000001101000 5
b0 &
13
1)
12
1(
1!
#556000
0%
1#
#560000
0!
#565000
03
0)
b0 '
b1 &
1!
#566000
1%
1$
0#
#570000
0!
#575000
b1 '
b0 &
03
0)
02
0(
1!
#576000
0%
0$
#580000
0!
#585000
13
1)
b0 '
b1 &
1!
#586000
1$
1#
#590000
0!
#595000
b1 '
b1101 4
bx1100011010101 6
bx0000011010001 5
b0 &
13
1)
12
1(
1!
#596000
1%
0$
0#
#600000
0!
#605000
03
0)
b0 '
b1 &
1!
#610000
0!
#615000
b1 '
b0 &
03
0)
02
0(
1!
#616000
0%
#620000
0!
#625000
13
1)
b0 '
b1 &
1!
#626000
1%
1#
#630000
0!
#635000
b1 '
b1110 4
bx11000110101010 6
bx00000110100011 5
b0 &
13
1)
12
1(
1!
#636000
0%
#640000
0!
#645000
03
0)
b0 '
b1 &
1!
#646000
1%
0#
#650000
0!
#655000
b1 '
b0 &
03
0)
02
0(
1!
#656000
0%
#660000
0!
#665000
13
1)
b0 '
b1 &
1!
#666000
1%
1$
#670000
0!
#675000
b11 1
b1 '
b1111 4
bx110001101010101 6
bx000001101000110 5
b0 &
13
1)
12
1(
1!
#676000
0$
1#
#680000
0!
#685000
03
0)
b0 '
b1 &
1!
#686000
0%
1$
#690000
0!
#695000
b1 '
b0 &
03
0)
02
0(
1!
#696000
1%
0#
#700000
0!
#705000
13
1)
b0 '
b1 &
1!
#706000
1#
#710000
0!
#715000
1.
10
0/
b1 '
b11 *
b0 4
b1100011010101011 6
b11010001101 5
b0 &
13
1)
12
1(
1!
#716000
0#
#720000
0!
#725000
03
0)
b0 '
b1 &
1!
#726000
b0 1
0%
0$
#730000
0!
#735000
b1 '
b0 &
03
0)
02
0(
1!
#736000
b11 1
1%
1$
#740000
0!
#745000
13
1)
b0 '
b1 &
1!
#746000
0$
#750000
0!
#755000
b1 '
b1101010101 ,
b1101000110 +
b0 &
13
1)
12
1(
1!
#760000
0!
#765000
03
0)
b0 '
b1 &
1!
#770000
0!
#775000
b1 '
b0 &
03
0)
02
0(
1!
#780000
0!
#785000
13
1)
b0 '
b1 &
1!
#786000
b0 1
0%
1$
1#
#790000
0!
#795000
0.
1-
b1 '
b0 *
b0 &
13
1)
12
1(
1!
#796000
b1 1
1%
0$
0#
#800000
0!
#805000
03
0)
b0 '
b1 &
1!
#810000
0!
#815000
b1 '
b0 &
03
0)
02
0(
1!
#816000
b0 1
0%
#820000
0!
#825000
13
1)
b0 '
b1 &
1!
#826000
1$
#830000
0!
#835000
b1 '
b0 &
13
1)
12
1(
1!
#836000
b1 1
1%
0$
#840000
0!
#845000
03
0)
b0 '
b1 &
1!
#846000
1#
#850000
0!
#855000
b1 '
b0 &
03
0)
02
0(
1!
#856000
1$
#860000
0!
#865000
13
1)
b0 '
b1 &
1!
#866000
0#
#870000
0!
#875000
00
0-
1/
b1 '
b1 *
b0 &
13
1)
12
1(
1!
#876000
0%
0$
1#
#880000
0!
#885000
03
0)
b0 '
b1 &
1!
#890000
0!
#895000
b1 '
b0 &
03
0)
02
0(
1!
#896000
1$
#900000
0!
#905000
13
1)
b0 '
b1 &
1!
#906000
0#
#910000
0!
#915000
b1 '
b1 4
b1000110101010111 6
b110100011010 5
b0 &
13
1)
12
1(
1!
#920000
0!
#925000
03
0)
b0 '
b1 &
1!
#926000
1#
#930000
0!
#935000
b1 '
b0 &
03
0)
02
0(
1!
#936000
1%
0$
#940000
0!
#945000
13
1)
b0 '
b1 &
1!
#946000
0#
#950000
0!
#955000
b1 '
b10 4
b1101010101110 6
b1101000110100 5
b0 &
13
1)
12
1(
1!
#956000
0%
#960000
0!
#965000
03
0)
b0 '
b1 &
1!
#966000
1%
1$
1#
#970000
0!
#975000
b1 '
b0 &
03
0)
02
0(
1!
#976000
0%
#980000
0!
#985000
13
1)
b0 '
b1 &
1!
#986000
1%
#990000
0!
#995000
b1 '
b11 4
b11010101011101 6
b11010001101001 5
b0 &
13
1)
12
1(
1!
#996000
0%
0$
0#
#1000000
0!
#1005000
03
0)
b0 '
b1 &
1!
#1010000
0!
#1015000
b1 '
b0 &
03
0)
02
0(
1!
#1016000
1%
1$
1#
#1020000
0!
#1025000
13
1)
b0 '
b1 &
1!
#1030000
0!
#1035000
b1 '
b100 4
b110101010111011 6
b110100011010011 5
b0 &
13
1)
12
1(
1!
#1036000
0$
#1040000
0!
#1045000
03
0)
b0 '
b1 &
1!
#1046000
1$
#1050000
0!
#1055000
b1 '
b0 &
03
0)
02
0(
1!
#1060000
0!
#1065000
13
1)
b0 '
b1 &
1!
#1066000
0%
0$
#1070000
0!
#1075000
b1 '
b101 4
b1101010101110110 6
b1101000110100111 5
b0 &
13
1)
12
1(
1!
#1076000
1$
#1080000
0!
#1085000
03
0)
b0 '
b1 &
1!
#1086000
0$
0#
#1090000
0!
#1095000
b1 '
b0 &
03
0)
02
0(
1!
#1096000
1#
#1100000
0!
#1105000
13
1)
b0 '
b1 &
1!
#1106000
0#
#1110000
0!
#1115000
b1 '
b110 4
b1010101011101100 6
b1010001101001110 5
b0 &
13
1)
12
1(
1!
#1116000
1$
#1120000
0!
#1125000
03
0)
b0 '
b1 &
1!
#1130000
0!
#1135000
b1 '
b0 &
03
0)
02
0(
1!
#1136000
0$
#1140000
0!
#1145000
13
1)
b0 '
b1 &
1!
#1146000
1%
1$
1#
#1150000
0!
#1155000
b1 '
b111 4
b101010111011001 6
b100011010011101 5
b0 &
13
1)
12
1(
1!
#1156000
0%
#1160000
0!
#1165000
03
0)
b0 '
b1 &
1!
#1166000
1%
#1170000
0!
#1175000
b1 '
b0 &
03
0)
02
0(
1!
#1176000
0%
0#
#1180000
0!
#1185000
13
1)
b0 '
b1 &
1!
#1186000
1%
#1190000
0!
#1195000
b1 '
b1000 4
b1010101110110011 6
b1000110100111010 5
b0 &
13
1)
12
1(
1!
#1196000
0%
#1200000
0!
#1205000
03
0)
b0 '
b1 &
1!
#1210000
0!
#1215000
b1 '
b0 &
03
0)
02
0(
1!
#1216000
0$
#1220000
0!
#1225000
13
1)
b0 '
b1 &
1!
#1226000
1%
1$
1#
#1230000
0!
#1235000
b1 '
b1001 4
b101011101100111 6
b1101001110101 5
b0 &
13
1)
12
1(
1!
#1236000
0$
#1240000
0!
#1245000
03
0)
b0 '
b1 &
1!
#1246000
1$
#1250000
0!
#1255000
b1 '
b0 &
03
0)
02
0(
1!
#1260000
0!
#1265000
13
1)
b0 '
b1 &
1!
#1266000
0%
0#
#1270000
0!
#1275000
b1 '
b1010 4
b1010111011001111 6
b11010011101010 5
b0 &
13
1)
12
1(
1!
#1276000
0$
1#
#1280000
0!
#1285000
03
0)
b0 '
b1 &
1!
#1290000
0!
#1295000
b1 '
b0 &
03
0)
02
0(
1!
#1296000
0#
#1300000
0!
#1305000
13
1)
b0 '
b1 &
1!
#1306000
1#
#1310000
0!
#1315000
b1 '
b1011 4
b101110110011110 6
b110100111010101 5
b0 &
13
1)
12
1(
1!
#1316000
0#
#1320000
0!
#1325000
03
0)
b0 '
b1 &
1!
#1326000
1$
#1330000
0!
#1335000
b1 '
b0 &
03
0)
02
0(
1!
#1336000
0$
1#
#1340000
0!
#1345000
13
1)
b0 '
b1 &
1!
#1346000
1%
#1350000
0!
#1355000
b1 '
b1100 4
b1011101100111100 6
b1101001110101011 5
b0 &
13
1)
12
1(
1!
#1360000
0!
#1365000
03
0)
b0 '
b1 &
1!
#1366000
0%
1$
0#
#1370000
0!
#1375000
b1 '
b0 &
03
0)
02
0(
1!
#1376000
0$
#1380000
0!
#1385000
13
1)
b0 '
b1 &
1!
#1386000
1%
1#
#1390000
0!
#1395000
b1 '
b1101 4
b111011001111000 6
b1010011101010111 5
b0 &
13
1)
12
1(
1!
#1396000
1$
0#
#1400000
0!
#1405000
03
0)
b0 '
b1 &
1!
#1406000
0%
#1410000
0!
#1415000
b1 '
b0 &
03
0)
02
0(
1!
#1416000
1%
1#
#1420000
0!
#1425000
13
1)
b0 '
b1 &
1!
#1426000
0#
#1430000
0!
#1435000
b1 '
b1110 4
b1110110011110001 6
b100111010101110 5
b0 &
13
1)
12
1(
1!
#1436000
0$
#1440000
0!
#1445000
03
0)
b0 '
b1 &
1!
